<?xml version="1.0" encoding="UTF-8"?>
<record_update table="sp_instance">
    <sp_instance action="INSERT_OR_UPDATE">
        <active>true</active>
        <class_name/>
        <color>default</color>
        <css/>
        <glyph/>
        <id/>
        <order>1</order>
        <roles/>
        <short_description/>
        <size>md</size>
        <sp_column display_value="1">69aa029adb6303007506771c8c9619b0</sp_column>
        <sp_widget display_value="zeit_zaehler">d2244a92db2303007506771c8c961987</sp_widget>
        <sys_class_name>sp_instance</sys_class_name>
        <sys_created_by>admin</sys_created_by>
        <sys_created_on>2018-01-11 11:45:52</sys_created_on>
        <sys_id>08ba4e5adb6303007506771c8c961923</sys_id>
        <sys_mod_count>0</sys_mod_count>
        <sys_name/>
        <sys_package display_value="Karteikasten" source="x_183655_karteikas">7fd11715dbaf03007506771c8c961915</sys_package>
        <sys_policy/>
        <sys_scope display_value="Karteikasten">7fd11715dbaf03007506771c8c961915</sys_scope>
        <sys_update_name>sp_instance_08ba4e5adb6303007506771c8c961923</sys_update_name>
        <sys_updated_by>admin</sys_updated_by>
        <sys_updated_on>2018-01-11 11:45:52</sys_updated_on>
        <title/>
        <url/>
        <widget_parameters/>
    </sp_instance>
    <sys_translated_text action="delete_multiple" query="documentkey=08ba4e5adb6303007506771c8c961923"/>
</record_update>
